tkinter_unblur/__init__.py
tkinter_unblur/__main__.py
tkinter_unblur/_windows.py
tkinter_unblur/core.py
tkinter_unblur/exceptions.py
tkinter_unblur/py.typed
tkinter_unblur-2.0.1.dist-info/licenses/LICENSE
tkinter_unblur-2.0.1.dist-info/METADATA
tkinter_unblur-2.0.1.dist-info/WHEEL
tkinter_unblur-2.0.1.dist-info/top_level.txt
tkinter_unblur-2.0.1.dist-info/RECORD
