Metadata-Version: 2.4
Name: tkinter-unblur
Version: 2.0.1
Summary: Fix blurry Tkinter applications on Windows 10/11 high-DPI displays
Author-email: unlibra <your.email@example.com>
License: MIT
Project-URL: Homepage, https://github.com/unlibra/tkinter-unblur
Project-URL: Documentation, https://github.com/unlibra/tkinter-unblur#readme
Project-URL: Repository, https://github.com/unlibra/tkinter-unblur
Project-URL: Issues, https://github.com/unlibra/tkinter-unblur/issues
Project-URL: Changelog, https://github.com/unlibra/tkinter-unblur/releases
Keywords: tkinter,blurry,dpi,hidpi,high-dpi,windows,scaling,gui,clear,sharp,pixelated,resolution
Classifier: Development Status :: 5 - Production/Stable
Classifier: Intended Audience :: Developers
Classifier: License :: OSI Approved :: MIT License
Classifier: Operating System :: Microsoft :: Windows
Classifier: Operating System :: OS Independent
Classifier: Programming Language :: Python :: 3
Classifier: Programming Language :: Python :: 3.9
Classifier: Programming Language :: Python :: 3.10
Classifier: Programming Language :: Python :: 3.11
Classifier: Programming Language :: Python :: 3.12
Classifier: Programming Language :: Python :: 3.13
Classifier: Programming Language :: Python :: 3.14
Classifier: Topic :: Software Development :: Libraries :: Python Modules
Classifier: Topic :: Software Development :: User Interfaces
Classifier: Typing :: Typed
Requires-Python: >=3.9
License-File: LICENSE
Provides-Extra: dev
Requires-Dist: pytest>=7.0; extra == "dev"
Requires-Dist: pytest-cov>=4.0; extra == "dev"
Requires-Dist: mypy>=1.0; extra == "dev"
Requires-Dist: ruff>=0.1.0; extra == "dev"
Dynamic: license-file
